curses_minesweeper/__init__.py
curses_minesweeper/game.py
curses_minesweeper/utils.py
curses_minesweeper-1.0.0.dist-info/entry_points.txt
curses_minesweeper-1.0.0.dist-info/licenses/LICENSE
curses_minesweeper-1.0.0.dist-info/WHEEL
curses_minesweeper-1.0.0.dist-info/METADATA
curses_minesweeper-1.0.0.dist-info/RECORD
