Metadata-Version: 2.4
Name: curses_minesweeper
Version: 1.0.0
Summary: (yet another) Minesweeper implementation with curses, cuz why not
Keywords: curses,minesweeper,cli-game
Author-email: nokarm567 <nokarm567@gmail.com>
Requires-Python: >=3.9
License-Expression: MIT
Classifier: Development Status :: 3 - Alpha
Classifier: Programming Language :: Python :: 3
Classifier: Operating System :: OS Independent
Classifier: Environment :: Console :: Curses
Classifier: Intended Audience :: End Users/Desktop
Classifier: Natural Language :: English
Classifier: Topic :: Games/Entertainment
License-File: LICENSE
Requires-Dist: windows-curses; sys_platform == 'win32'
